{
  "ghostbusters": [
    {
      "source": "How I Met Your Mother",
      "episode": "How I Met Your Mother - 1x01",
      "line": "Can quote obscure lines from Ghostbusters ?"
    },
    {
      "source": "How I Met Your Mother",
      "episode": "How I Met Your Mother - 7x11",
      "line": "Who you gonna call?"
    },
    {
      "source": "How I Met Your Mother",
      "episode": "How I Met Your Mother - 7x22",
      "line": "<i>favorite poet Neruda,</i> <i>favorite movie</i> Ghostbusters,"
    }
  ],
  "star wars": [
    {
      "source": "How I Met Your Mother",
      "episode": "How I Met Your Mother - 1x06",
      "line": "She's funny, she's beautiful, she loves Star Wars."
    },
    {
      "source": "How I Met Your Mother",
      "episode": "How I Met Your Mother - 1x19",
      "line": "Hey, you know that scene in Empire where they lower the helmet onto Darth Vader's head?"
    },
    {
      "source": "How I Met Your Mother",
      "episode": "How I Met Your Mother - 3x05",
      "line": "No, The Force. It's a Star Wars reference."
    },
    {
      "source": "How I Met Your Mother",
      "episode": "How I Met Your Mother - 3x05",
      "line": "So we should make lots of Star Wars references around girls."
    },
    {
      "source": "How I Met Your Mother",
      "episode": "How I Met Your Mother - 4x06",
      "line": "Stella hated star wars. She lied to you."
    },
    {
      "source": "How I Met Your Mother",
      "episode": "How I Met Your Mother - 4x07",
      "line": "from the Cantina scene in Star Wars."
    },
    {
      "source": "How I Met Your Mother",
      "episode": "How I Met Your Mother - 5x07",
      "line": "Number three, The Star Wars Altercation."
    },
    {
      "source": "How I Met Your Mother",
      "episode": "How I Met Your Mother - 5x07",
      "line": "- Nobody says that in Star Wars at all. - That's a really lousy robot voice."
    },
    {
      "source": "How I Met Your Mother",
      "episode": "How I Met Your Mother - 6x03",
      "line": "GNB is the Empire from Star Wars."
    },
    {
      "source": "How I Met Your Mother",
      "episode": "How I Met Your Mother - 7x05",
      "line": "at least ten years old when Jedi came out,"
    },
    {
      "source": "How I Met Your Mother",
      "episode": "How I Met Your Mother - 9x15",
      "line": "<i>Jabba the Hutt from</i> Return of the Jedi."
    },
    {
      "source": "How I Met Your Mother",
      "episode": "How I Met Your Mother - 9x17",
      "line": "It's Tatooine scrap metal!"
    }
  ],
  "star wars: episode vi - return of the jedi": [
    {
      "source": "How I Met Your Mother",
      "episode": "How I Met Your Mother - 1x06",
      "line": "Whoa, whoa, whoa, whoa, what's her take on Ewoks?"
    },
    {
      "source": "How I Met Your Mother",
      "episode": "How I Met Your Mother - 1x06",
      "line": "I don't know why people are so cynical about Ewoks."
    },
    {
      "source": "How I Met Your Mother",
      "episode": "How I Met Your Mother - 1x06",
      "line": "The rebellion would have failed without the Ewoks."
    },
    {
      "source": "How I Met Your Mother",
      "episode": "How I Met Your Mother - 1x06",
      "line": "Kind of like black and white Ewoks."
    },
    {
      "source": "How I Met Your Mother",
      "episode": "How I Met Your Mother - 4x01",
      "line": "from the Death Star's trash compactor."
    },
    {
      "source": "How I Met Your Mother",
      "episode": "How I Met Your Mother - 5x07",
      "line": "When they blew up the Death Star, knowing full well there were thousands"
    },
    {
      "source": "How I Met Your Mother",
      "episode": "How I Met Your Mother - 5x07",
      "line": "It was called the Death Star. They knew what they were getting into."
    },
    {
      "source": "How I Met Your Mother",
      "episode": "How I Met Your Mother - 6x03",
      "line": "But the Death Star's gonna get built either way."
    },
    {
      "source": "How I Met Your Mother",
      "episode": "How I Met Your Mother - 6x03",
      "line": "Don't you think the architect of the Death Star"
    },
    {
      "source": "How I Met Your Mother",
      "episode": "How I Met Your Mother - 6x03",
      "line": "a giant exposed vent right over a Death Star's core reactor."
    },
    {
      "source": "How I Met Your Mother",
      "episode": "How I Met Your Mother - 7x05",
      "line": "until you agree to peaceably shut down the Death Star."
    },
    {
      "source": "How I Met Your Mother",
      "episode": "How I Met Your Mother - 7x05",
      "line": "Ewoks."
    },
    {
      "source": "How I Met Your Mother",
      "episode": "How I Met Your Mother - 7x05",
      "line": "Ugh, I hate the Ewoks."
    },
    {
      "source": "How I Met Your Mother",
      "episode": "How I Met Your Mother - 7x05",
      "line": "The only good thing about Ewoks in that movie?"
    },
    {
      "source": "How I Met Your Mother",
      "episode": "How I Met Your Mother - 7x05",
      "line": "Nora hates Ewoks."
    },
    {
      "source": "How I Met Your Mother",
      "episode": "How I Met Your Mother - 7x05",
      "line": "Not liking Ewoks"
    },
    {
      "source": "How I Met Your Mother",
      "episode": "How I Met Your Mother - 7x05",
      "line": "I mean, you're dating a girl who doesn't like Ewoks,"
    },
    {
      "source": "How I Met Your Mother",
      "episode": "How I Met Your Mother - 7x05",
      "line": "But she doesn't like Ewoks!"
    },
    {
      "source": "How I Met Your Mother",
      "episode": "How I Met Your Mother - 7x05",
      "line": "In 1983, George Lucas introduced the world to the Ewoks,"
    },
    {
      "source": "How I Met Your Mother",
      "episode": "How I Met Your Mother - 7x05",
      "line": "a race of creatures indigenous to the second moon of Endor."
    },
    {
      "source": "How I Met Your Mother",
      "episode": "How I Met Your Mother - 7x05",
      "line": "Now, the Ewoks have a rich back-story"
    },
    {
      "source": "How I Met Your Mother",
      "episode": "How I Met Your Mother - 7x05",
      "line": "Ultimately, Ewoks split <i>Star</i> <i>Wars</i> fandom into two camps:"
    },
    {
      "source": "How I Met Your Mother",
      "episode": "How I Met Your Mother - 7x05",
      "line": "Anyone born on this side loved the Ewoks because, why?"
    },
    {
      "source": "How I Met Your Mother",
      "episode": "How I Met Your Mother - 7x05",
      "line": "my 29-year-old girlfriend who hates Ewoks"
    },
    {
      "source": "How I Met Your Mother",
      "episode": "How I Met Your Mother - 7x05",
      "line": "the first time you saw the Ewoks and you would have loved them."
    },
    {
      "source": "How I Met Your Mother",
      "episode": "How I Met Your Mother - 9x10",
      "line": "Well, that and my own operational Death Star."
    }
  ],
  "the godfather": [
    {
      "source": "How I Met Your Mother",
      "episode": "How I Met Your Mother - 1x06",
      "line": "So this Italian place, how is their cannoli?"
    }
  ],
  "the lion king": [
    {
      "source": "How I Met Your Mother",
      "episode": "How I Met Your Mother - 1x14",
      "line": "It's the circle of life."
    },
    {
      "source": "How I Met Your Mother",
      "episode": "How I Met Your Mother - 7x01",
      "line": "Hakuna Matata!"
    }
  ],
  "the lord of the rings: the fellowship of the ring": [
    {
      "source": "How I Met Your Mother",
      "episode": "How I Met Your Mother - 1x16",
      "line": "I've just been offered a fellowship at a culinary institute in Germany."
    },
    {
      "source": "How I Met Your Mother",
      "episode": "How I Met Your Mother - 1x16",
      "line": "what to do about your doughnut fellowship?"
    },
    {
      "source": "How I Met Your Mother",
      "episode": "How I Met Your Mother - 1x21",
      "line": "and I found that art fellowship."
    },
    {
      "source": "How I Met Your Mother",
      "episode": "How I Met Your Mother - 1x22",
      "line": "I'm pleased to inform you that we've accepted your application for our summer fellowship."
    },
    {
      "source": "How I Met Your Mother",
      "episode": "How I Met Your Mother - 1x22",
      "line": "Summer fellowship?"
    },
    {
      "source": "How I Met Your Mother",
      "episode": "How I Met Your Mother - 1x22",
      "line": "- A painting fellowship? - I was never going to take it."
    },
    {
      "source": "How I Met Your Mother",
      "episode": "How I Met Your Mother - 8x14",
      "line": "it's like when Bilbo Baggins wears the One Ring"
    },
    {
      "source": "How I Met Your Mother",
      "episode": "How I Met Your Mother - 9x05",
      "line": "one ring."
    }
  ],
  "Friends": [
    {
      "source": "How I Met Your Mother",
      "episode": "How I Met Your Mother - 1x17",
      "line": "How you doing?"
    },
    {
      "source": "How I Met Your Mother",
      "episode": "How I Met Your Mother - 2x02",
      "line": "How you doing?"
    },
    {
      "source": "How I Met Your Mother",
      "episode": "How I Met Your Mother - 6x13",
      "line": "How you doing?!"
    },
    {
      "source": "How I Met Your Mother",
      "episode": "How I Met Your Mother - 6x22",
      "line": "How you doin'?"
    },
    {
      "source": "How I Met Your Mother",
      "episode": "How I Met Your Mother - 9x01",
      "line": "How are you doing?"
    },
    {
      "source": "How I Met Your Mother",
      "episode": "How I Met Your Mother - 9x15",
      "line": "How you doin'?"
    }
  ],
  "Toy Story": [
    {
      "source": "How I Met Your Mother",
      "episode": "How I Met Your Mother - 1x18",
      "line": "Infinity."
    },
    {
      "source": "How I Met Your Mother",
      "episode": "How I Met Your Mother - 5x15",
      "line": "Infinity."
    }
  ],
  "die hard": [
    {
      "source": "How I Met Your Mother",
      "episode": "How I Met Your Mother - 2x04",
      "line": "Maybe a great movie like Die Hard."
    },
    {
      "source": "How I Met Your Mother",
      "episode": "How I Met Your Mother - 4x15",
      "line": "- Who do you root for in <i>Die Hard</i>? - Hans Gruber,"
    }
  ],
  "Taxi Driver": [
    {
      "source": "How I Met Your Mother",
      "episode": "How I Met Your Mother - 2x07",
      "line": "I'm talking to you."
    },
    {
      "source": "How I Met Your Mother",
      "episode": "How I Met Your Mother - 3x11",
      "line": "Oh, so you're talking to me now?"
    }
  ],
  "Breaking Bad": [
    {
      "source": "How I Met Your Mother",
      "episode": "How I Met Your Mother - 2x07",
      "line": "Say the name."
    }
  ],
  "Dirty Dancing": [
    {
      "source": "How I Met Your Mother",
      "episode": "How I Met Your Mother - 2x12",
      "line": "- Did anyone put Baby in a corner? - Oh, God, no."
    }
  ],
  "The Simpsons": [
    {
      "source": "How I Met Your Mother",
      "episode": "How I Met Your Mother - 2x13",
      "line": "Drop your shorts."
    }
  ],
  "inception": [
    {
      "source": "How I Met Your Mother",
      "episode": "How I Met Your Mother - 2x22",
      "line": "Horrible wedding clichés we're not going to touch with a ten-foot limbo pole."
    },
    {
      "source": "How I Met Your Mother",
      "episode": "How I Met Your Mother - 4x18",
      "line": "\"Saskatoon Totem Pole.\""
    },
    {
      "source": "How I Met Your Mother",
      "episode": "How I Met Your Mother - 6x09",
      "line": "But check your totem, brah. Punchy's here in the flesh."
    },
    {
      "source": "How I Met Your Mother",
      "episode": "How I Met Your Mother - 7x05",
      "line": "and we're here doing the limbo?"
    },
    {
      "source": "How I Met Your Mother",
      "episode": "How I Met Your Mother - 7x05",
      "line": "to hold the other end of the limbo stick,"
    },
    {
      "source": "How I Met Your Mother",
      "episode": "How I Met Your Mother - 7x21",
      "line": "trying to inception your wife."
    }
  ],
  "The Office": [
    {
      "source": "How I Met Your Mother",
      "episode": "How I Met Your Mother - 2x22",
      "line": "That's what she said."
    },
    {
      "source": "How I Met Your Mother",
      "episode": "How I Met Your Mother - 3x04",
      "line": "That's what I said."
    }
  ],
  "star wars: episode v - the empire strikes back": [
    {
      "source": "How I Met Your Mother",
      "episode": "How I Met Your Mother - 3x05",
      "line": "Think of me as Yoda,"
    },
    {
      "source": "How I Met Your Mother",
      "episode": "How I Met Your Mother - 4x13",
      "line": "-but it's like Hoth out there. -Dibs."
    },
    {
      "source": "How I Met Your Mother",
      "episode": "How I Met Your Mother - 6x21",
      "line": "I am not going to buckle up! I am your father! You will listen to me!"
    }
  ],
  "the dark knight": [
    {
      "source": "How I Met Your Mother",
      "episode": "How I Met Your Mother - 3x07",
      "line": "but there's a reason your name is Robin, not Batman."
    },
    {
      "source": "How I Met Your Mother",
      "episode": "How I Met Your Mother - 4x09",
      "line": "I mean,I'm like Batman."
    },
    {
      "source": "How I Met Your Mother",
      "episode": "How I Met Your Mother - 5x02",
      "line": "And here's a picture of my cats dressed up like Batman villains."
    },
    {
      "source": "How I Met Your Mother",
      "episode": "How I Met Your Mother - 6x05",
      "line": "I'm Batman."
    },
    {
      "source": "How I Met Your Mother",
      "episode": "How I Met Your Mother - 7x04",
      "line": "We're right up there with Batman and Robin and Alfred."
    },
    {
      "source": "How I Met Your Mother",
      "episode": "How I Met Your Mother - 7x13",
      "line": "where Gotham's intelligentsia hold court"
    },
    {
      "source": "How I Met Your Mother",
      "episode": "How I Met Your Mother - 9x18",
      "line": "...of Gotham City..."
    },
    {
      "source": "How I Met Your Mother",
      "episode": "How I Met Your Mother - 9x18",
      "line": "...I vow to make Batman work harder."
    }
  ],
  "jurassic park": [
    {
      "source": "How I Met Your Mother",
      "episode": "How I Met Your Mother - 3x08",
      "line": "We had ribs the other night. It sounded like Jurassic Park."
    },
    {
      "source": "How I Met Your Mother",
      "episode": "How I Met Your Mother - 5x06",
      "line": "There's a glass of water in my bedroom that's vibrating like Jurassic Park."
    },
    {
      "source": "How I Met Your Mother",
      "episode": "How I Met Your Mother - 6x24",
      "line": "<i>she sounds like a velociraptor from Jurassic Park.</i>"
    },
    {
      "source": "How I Met Your Mother",
      "episode": "How I Met Your Mother - 8x14",
      "line": "And you spared no expense, you big crazy!"
    }
  ],
  "titanic": [
    {
      "source": "How I Met Your Mother",
      "episode": "How I Met Your Mother - 3x12",
      "line": "It's like the last 20 minutes of Titanic in here."
    }
  ],
  "interstellar": [
    {
      "source": "How I Met Your Mother",
      "episode": "How I Met Your Mother - 3x12",
      "line": "philosophical wormhole."
    },
    {
      "source": "How I Met Your Mother",
      "episode": "How I Met Your Mother - 5x19",
      "line": "Oh, yeah, well, our spaceship passed through a wormhole"
    }
  ],
  "breaking bad": [
    {
      "source": "How I Met Your Mother",
      "episode": "How I Met Your Mother - 3x15",
      "line": "Shh, don't say my name."
    }
  ],
  "the notebook": [
    {
      "source": "How I Met Your Mother",
      "episode": "How I Met Your Mother - 4x04",
      "line": "No, they're like love letters or yearbooks or someone's ashes."
    },
    {
      "source": "How I Met Your Mother",
      "episode": "How I Met Your Mother - 4x09",
      "line": "and just finished reading The Notebook"
    },
    {
      "source": "How I Met Your Mother",
      "episode": "How I Met Your Mother - 5x03",
      "line": "Here, I'll get rid of the notebook."
    }
  ],
  "Lethal Weapon": [
    {
      "source": "How I Met Your Mother",
      "episode": "How I Met Your Mother - 4x19",
      "line": "I'm too old for this..."
    },
    {
      "source": "How I Met Your Mother",
      "episode": "How I Met Your Mother - 4x19",
      "line": "I'm too old for that stuff."
    },
    {
      "source": "How I Met Your Mother",
      "episode": "How I Met Your Mother - 4x19",
      "line": "I'm too old for this stuff."
    }
  ],
  "Lost in Space": [
    {
      "source": "How I Met Your Mother",
      "episode": "How I Met Your Mother - 5x07",
      "line": "Greetings, Will Robinson!"
    }
  ],
  "the departed": [
    {
      "source": "How I Met Your Mother",
      "episode": "How I Met Your Mother - 5x19",
      "line": "At the corner of abbott and costello. No."
    }
  ],
  "the social network": [
    {
      "source": "How I Met Your Mother",
      "episode": "How I Met Your Mother - 6x03",
      "line": "And that Asian slut on your Facebook page. She's dead, too."
    },
    {
      "source": "How I Met Your Mother",
      "episode": "How I Met Your Mother - 6x09",
      "line": "You see? I read your Facebook updates."
    },
    {
      "source": "How I Met Your Mother",
      "episode": "How I Met Your Mother - 7x01",
      "line": "or B) claiming that I also invented Facebook"
    },
    {
      "source": "How I Met Your Mother",
      "episode": "How I Met Your Mother - 7x06",
      "line": "Total psycho. Her Facebook wall"
    },
    {
      "source": "How I Met Your Mother",
      "episode": "How I Met Your Mother - 7x08",
      "line": "I was on Facebook."
    },
    {
      "source": "How I Met Your Mother",
      "episode": "How I Met Your Mother - 7x08",
      "line": "Nobody cool's on Facebook anymore."
    },
    {
      "source": "How I Met Your Mother",
      "episode": "How I Met Your Mother - 7x08",
      "line": "Well, you know who is on Facebook now?"
    },
    {
      "source": "How I Met Your Mother",
      "episode": "How I Met Your Mother - 8x10",
      "line": "I want to change my Facebook status to \"happy!\""
    },
    {
      "source": "How I Met Your Mother",
      "episode": "How I Met Your Mother - 8x11",
      "line": "I mean, I'm sort of the Mark Zuckerberg"
    },
    {
      "source": "How I Met Your Mother",
      "episode": "How I Met Your Mother - 8x13",
      "line": "It's on my Facebook page."
    },
    {
      "source": "How I Met Your Mother",
      "episode": "How I Met Your Mother - 8x13",
      "line": "No, I'm, uh, talking about your Facebook page?"
    },
    {
      "source": "How I Met Your Mother",
      "episode": "How I Met Your Mother - 8x13",
      "line": "I Facebooked it... on Facebook."
    },
    {
      "source": "How I Met Your Mother",
      "episode": "How I Met Your Mother - 8x24",
      "line": "Oh, yeah? Well, check out what's already on facebook."
    },
    {
      "source": "How I Met Your Mother",
      "episode": "How I Met Your Mother - 9x09",
      "line": "I will live on your Facebook wall!"
    },
    {
      "source": "How I Met Your Mother",
      "episode": "How I Met Your Mother - 9x09",
      "line": "We're not Facebook friends."
    },
    {
      "source": "How I Met Your Mother",
      "episode": "How I Met Your Mother - 9x21",
      "line": "Perhaps you've seen their photos on Facebook."
    }
  ],
  "Captain Phillips": [
    {
      "source": "How I Met Your Mother",
      "episode": "How I Met Your Mother - 6x08",
      "line": "But you can, and should, call me The Captain."
    },
    {
      "source": "How I Met Your Mother",
      "episode": "How I Met Your Mother - 6x08",
      "line": "The Captain? The Captain?"
    },
    {
      "source": "How I Met Your Mother",
      "episode": "How I Met Your Mother - 6x11",
      "line": "Captain, quick question:"
    },
    {
      "source": "How I Met Your Mother",
      "episode": "How I Met Your Mother - 6x11",
      "line": "The Captain."
    },
    {
      "source": "How I Met Your Mother",
      "episode": "How I Met Your Mother - 6x11",
      "line": "Captain."
    },
    {
      "source": "How I Met Your Mother",
      "episode": "How I Met Your Mother - 6x15",
      "line": "I mean, The Captain."
    },
    {
      "source": "How I Met Your Mother",
      "episode": "How I Met Your Mother - 6x17",
      "line": "I ran into The Captain."
    },
    {
      "source": "How I Met Your Mother",
      "episode": "How I Met Your Mother - 8x06",
      "line": "I'm also the captain of a team"
    },
    {
      "source": "How I Met Your Mother",
      "episode": "How I Met Your Mother - 8x17",
      "line": "Captain?"
    },
    {
      "source": "How I Met Your Mother",
      "episode": "How I Met Your Mother - 8x19",
      "line": "Captain?"
    },
    {
      "source": "How I Met Your Mother",
      "episode": "How I Met Your Mother - 8x19",
      "line": "It's the Captain."
    },
    {
      "source": "How I Met Your Mother",
      "episode": "How I Met Your Mother - 8x21",
      "line": "Captain? Hello?"
    },
    {
      "source": "How I Met Your Mother",
      "episode": "How I Met Your Mother - 8x21",
      "line": "Okay, I'm gonna call The Captain,"
    },
    {
      "source": "How I Met Your Mother",
      "episode": "How I Met Your Mother - 8x21",
      "line": "to The Captain's right now!"
    },
    {
      "source": "How I Met Your Mother",
      "episode": "How I Met Your Mother - 9x20",
      "line": "Captain."
    }
  ],
  "Survivor": [
    {
      "source": "How I Met Your Mother",
      "episode": "How I Met Your Mother - 6x09",
      "line": "Punchy, the tribe has spoken."
    }
  ],
  "the simpsons": [
    {
      "source": "How I Met Your Mother",
      "episode": "How I Met Your Mother - 6x11",
      "line": "D'oh!"
    }
  ],
  "forrest gump": [
    {
      "source": "How I Met Your Mother",
      "episode": "How I Met Your Mother - 6x16",
      "line": "while wolfing down the box of chocolates you had delivered to yourself at work"
    },
    {
      "source": "How I Met Your Mother",
      "episode": "How I Met Your Mother - 6x16",
      "line": "I buy flowers and a box of chocolates, even if I'm not with someone."
    }
  ],
  "django unchained": [
    {
      "source": "How I Met Your Mother",
      "episode": "How I Met Your Mother - 6x19",
      "line": "It works its way up to Candyland, and then, congratulate me,"
    }
  ],
  "Seinfeld": [
    {
      "source": "How I Met Your Mother",
      "episode": "How I Met Your Mother - 6x24",
      "line": "Don't eat the soup!"
    }
  ],
  "Family Matters": [
    {
      "source": "How I Met Your Mother",
      "episode": "How I Met Your Mother - 7x08",
      "line": "I did?"
    }
  ],
  "The Maltese Falcon": [
    {
      "source": "How I Met Your Mother",
      "episode": "How I Met Your Mother - 7x21",
      "line": "Yeah, well, dreams are just stuff"
    }
  ],
  "the terminator": [
    {
      "source": "How I Met Your Mother",
      "episode": "How I Met Your Mother - 7x23",
      "line": "tried to pick up girls as the Terminator?"
    }
  ],
  "the silence of the lambs": [
    {
      "source": "How I Met Your Mother",
      "episode": "How I Met Your Mother - 8x11",
      "line": "<i>like in</i> The Silence of the Lambs."
    }
  ],
  "house of cards": [
    {
      "source": "How I Met Your Mother",
      "episode": "How I Met Your Mother - 8x21",
      "line": "It's a real house of cards."
    },
    {
      "source": "How I Met Your Mother",
      "episode": "How I Met Your Mother - 8x21",
      "line": "Is this the \"house of cards\" you were talking about?"
    }
  ],
  "Full House": [
    {
      "source": "How I Met Your Mother",
      "episode": "How I Met Your Mother - 9x05",
      "line": "You got it, buddy!"
    }
  ],
  "Titanic": [
    {
      "source": "How I Met Your Mother",
      "episode": "How I Met Your Mother - 9x11",
      "line": "am I king? Glad you asked."
    },
    {
      "source": "How I Met Your Mother",
      "episode": "How I Met Your Mother - 9x11",
      "line": "But I'm the king."
    }
  ],
  "Columbo": [
    {
      "source": "How I Met Your Mother",
      "episode": "How I Met Your Mother - 9x14",
      "line": "One other thing."
    }
  ]
}